tests/__init__.py
tests/common.py
tests/conftest.py
tests/test_utils.py
tests/recipes/__init__.py
tests/recipes/common.py
tests/recipes/test_alpaca_generate.py
tests/recipes/test_configs.py
tests/recipes/test_full_finetune.py
tests/recipes/test_lora_finetune.py
tests/recipes/utils.py
tests/torchtune/__init__.py
tests/torchtune/_cli/__init__.py
tests/torchtune/_cli/test_convert_checkpoint.py
tests/torchtune/_cli/test_cp.py
tests/torchtune/_cli/test_download.py
tests/torchtune/_cli/test_ls.py
tests/torchtune/_cli/test_tune.py
tests/torchtune/_cli/test_validate.py
tests/torchtune/datasets/__init__.py
tests/torchtune/datasets/test_alpaca_dataset.py
tests/torchtune/datasets/test_instruct_dataset.py
tests/torchtune/datasets/test_slimorca_dataset.py
tests/torchtune/generation/__init__.py
tests/torchtune/generation/test_generation.py
tests/torchtune/models/__init__.py
tests/torchtune/models/test_lora_llama2.py
tests/torchtune/modules/__init__.py
tests/torchtune/modules/test_attention.py
tests/torchtune/modules/test_cosine_with_warmup.py
tests/torchtune/modules/test_feed_forward.py
tests/torchtune/modules/test_position_embeddings.py
tests/torchtune/modules/test_rms_norm.py
tests/torchtune/modules/test_tokenizer.py
tests/torchtune/modules/test_transformer_decoder.py
tests/torchtune/modules/low_precision/__init__.py
tests/torchtune/modules/low_precision/test_nf4_linear.py
tests/torchtune/modules/peft/__init__.py
tests/torchtune/modules/peft/test_lora.py
tests/torchtune/modules/peft/test_peft_utils.py
tests/torchtune/utils/__init__.py
tests/torchtune/utils/test_argparse.py
tests/torchtune/utils/test_checkpoint.py
tests/torchtune/utils/test_checkpointable_dataloader.py
tests/torchtune/utils/test_checkpointer.py
tests/torchtune/utils/test_collate.py
tests/torchtune/utils/test_device.py
tests/torchtune/utils/test_distributed.py
tests/torchtune/utils/test_logits_transforms.py
tests/torchtune/utils/test_metric_logging.py
tests/torchtune/utils/test_precision.py
torchchat-0.0.1.dist-info/LICENSE
torchchat-0.0.1.dist-info/METADATA
torchchat-0.0.1.dist-info/WHEEL
torchchat-0.0.1.dist-info/entry_points.txt
torchchat-0.0.1.dist-info/top_level.txt
torchchat-0.0.1.dist-info/RECORD
